record_keeper/__init__.py
record_keeper/db_utils.py
record_keeper/record_keeper.py
record_keeper/utils.py
record_keeper-0.9.32.dist-info/METADATA
record_keeper-0.9.32.dist-info/WHEEL
record_keeper-0.9.32.dist-info/top_level.txt
record_keeper-0.9.32.dist-info/RECORD
