Metadata-Version: 2.1
Name: record-keeper
Version: 0.9.32
Summary: Record experiment data easily
Home-page: https://github.com/KevinMusgrave/record-keeper
Author: Kevin Musgrave
License: UNKNOWN
Platform: UNKNOWN
Classifier: Programming Language :: Python :: 3
Classifier: License :: OSI Approved :: MIT License
Classifier: Operating System :: OS Independent
Requires-Python: >=3.0
Requires-Dist: numpy
Requires-Dist: torch
